LICENSE
MANIFEST.in
README.md
requirements.txt
setup.py
keras_helper/__init__.py
keras_helper.egg-info/PKG-INFO
keras_helper.egg-info/SOURCES.txt
keras_helper.egg-info/dependency_links.txt
keras_helper.egg-info/top_level.txt
keras_helper.egg-info/zip-safe