Metadata-Version: 2.1
Name: keras-helper
Version: 1.0
Summary: Helpful Keras Import Wrapper
Home-page: https://github.com/guilt/keras-helper
Author: Karthik Kumar Viswanathan
Author-email: karthikkumar@gmail.com
License: MIT
Keywords: keras mxnet cntk plaidml tensorflow theano cuda numpy numpy-intel pandas ray modin scikit-learn matplotlib seaborn plotly helper ai ml datascience
Platform: UNKNOWN
Classifier: Topic :: Software Development :: Libraries :: Python Modules
